setup.py
VideoSpeed/__init__.py
VideoSpeed/__main__.py
VideoSpeed/cli.py
videospeed-1.0.4.dist-info/METADATA
videospeed-1.0.4.dist-info/WHEEL
videospeed-1.0.4.dist-info/entry_points.txt
videospeed-1.0.4.dist-info/top_level.txt
videospeed-1.0.4.dist-info/RECORD
