Metadata-Version: 2.4
Name: VideoSpeed
Version: 1.0.4
Summary: A command-line video editing tool built in Python for cutting, speeding up, and applying a boomerang effect to MP4 videos.
Author-email: Wilgat Wong <wilgat.wong@gmail.com>
License: MIT
Project-URL: Homepage, https://github.com/Wilgat/VideoSpeed
Project-URL: Repository, https://github.com/Wilgat/VideoSpeed
Project-URL: Issues, https://github.com/Wilgat/VideoSpeed/issues
Keywords: Video Editing,Multimeida
Requires-Python: !=3.0.*,!=3.1.*,!=3.2.*,!=3.3.*,!=3.4.*,>=2.7
Requires-Dist: ChronicleLogger>=1.2.3
Requires-Dist: opencv-python
